rtl/exceptions.svh
`ifndef CPU_EXCEPTIONS
`define CPU_EXCEPTIONS

package exceptions;

typedef enum logic[7:0] {

    NONE,

    PAGE_PRIVALIGED_ACCESS,
    PAGE_READ_ONLY,
    NO_PAGE_MAPPED,
    INVALID_PAGE_ENTRY,

    DIVIDE_BY_ZERO,

    INVALID_ADDRESS,
    INVALID_OPCODE,

    DOUBLE_FAULT,
    TRIPLE_FAULT,

    INVALID_FLOAT_SIZE,

    TIMER

} exception_t;
    
endpackage

`endif

rtl/requests.svh
`ifndef CPU_REQUEST
`define CPU_REQUEST

`include "rtl/types.svh"

import types::*;

package requests;

typedef struct packed {
    ulong_t addr;
    ulong_t data;
    logic isWrite;
    logic isPrivaliged;
    logic isValid;
} cpuMemRequest_t;

typedef struct packed {
    ulong_t data;
    logic isValid;
} cpuMemResult_t;

endpackage

`endif

rtl/types.svh
`ifndef CPU_TYPES
`define CPU_TYPES

package types;

typedef logic signed[7:0] byte_t;
typedef logic signed[15:0] short_t;
typedef logic signed[31:0] int_t;
typedef logic signed[63:0] long_t;

typedef logic unsigned[7:0] ubyte_t;
typedef logic unsigned[15:0] ushort_t;
typedef logic unsigned[31:0] uint_t;
typedef logic unsigned[63:0] ulong_t;

typedef struct packed {
    logic sign;
    logic[4:0] exponent;
    logic[9:0] fraction;
} half_t;

typedef struct packed {
    logic sign;
    logic[7:0] exponent;
    logic[22:0] fraction;
} single_t;

typedef struct packed {
    logic sign;
    logic[10:0] exponent;
    logic[51:0] fraction;
} double_t;

typedef enum logic[1:0] {
    HALF,
    SINGLE,
    DOUBLE
} floatType_t;

typedef union packed {
    half_t half;
    single_t single;
    double_t double;
} floatValue_t;

typedef struct packed {
    floatType_t ftype;
    floatValue_t value;
} float_t;

endpackage

`endif

tests/testing.svh
`ifndef TESTING
`define TESTING

`define DO_TEST(value, expected, name) \
if (value == expected) \
    $display("Passed (%s, %0d [%0d]): %s", `__FILE__, `__LINE__, $realtime, name); \
else \
    $display("Failed (%s, %0d [%0d]): %s", `__FILE__, `__LINE__, $realtime, name);

`endif

rtl/mmu/mmu.sv
`include "rtl/types.svh"
`include "rtl/requests.svh"
`include "rtl/exceptions.svh"

import types::*;
import requests::*;
import exceptions::*;

`define PAGE_FLAG_PRESENT   12'b000000000001
`define PAGE_FLAG_SIZE      12'b000000000010
`define PAGE_FLAG_PRIVALIGE 12'b000000000100
`define PAGE_FLAG_WRITE     12'b000000001000

`define KB_SIZE     12
`define MB_SIZE     9
`define GB_SIZE     9
`define ENTRIES     512

`define KB 0
`define MB 1
`define GB 2
`define UNUSED 3

typedef logic[1:0] PageSize;

typedef struct packed {
    ulong_t virtualAddr, physicalAddr;
    PageSize size;
    logic isPrivaliged;
    logic canWrite;
    logic isValid;
} TLEntry;

typedef enum logic[1:0] {
    IDLE,
    LOOKUP_PT0,
    LOOKUP_PT1,
    LOOKUP_PT2
} MMUStage;

module MMU #(
    parameter TLBEntries = 8
) (
    input logic clock, reset,

    input logic enabled,
    input ulong_t pageTableAddr,

    input cpuMemRequest_t cpu_request,
    output cpuMemResult_t cpu_result,
    output exception_t cpu_exception,

    output cpuMemRequest_t mem_request,
    input cpuMemResult_t mem_result
);

    TLEntry[TLBEntries - 1:0] buffer;
    logic[$clog2(TLBEntries)-1:0] counter;
    MMUStage stage;

    integer i;

    // TLB entrys reset

    always @(posedge reset) begin
        for (i = 0; i < TLBEntries; i = i + 1) begin
            buffer[i] <= {64'h0, 64'h0, 1'b0, 1'b0, 1'b0};
        end

        counter <= 0;
    end

    // Other reset

    always @(posedge reset) begin
        stage <= IDLE;

        cpu_result.isValid <= 0;
        cpu_exception <= NONE;
        mem_request.isValid <= 0;

        passResult <= 0;
        foundEntry <= 0;
    end
    
    ulong_t GBAddr;
    ulong_t MBAddr;
    ulong_t KBAddr;

    // TODO: Double check these values!
    always @* begin
        GBAddr <= {cpu_request.addr[63:`KB_SIZE+`MB_SIZE+`GB_SIZE], {(`KB_SIZE+`MB_SIZE+`GB_SIZE){1'b0}}};
        MBAddr <= {cpu_request.addr[63:`KB_SIZE+`MB_SIZE], {(`KB_SIZE+`MB_SIZE){1'b0}}};
        KBAddr <= {cpu_request.addr[63:`KB_SIZE], {`KB_SIZE{1'b0}}};
    end

    ulong_t GBOffset;
    ulong_t MBOffset;
    ulong_t KBOffset;

    // TODO: Double check these values!
    always @* begin
        GBOffset <= {{(64-`KB_SIZE-`MB_SIZE-`GB_SIZE){1'b0}}, cpu_request.addr[`KB_SIZE+`MB_SIZE+`GB_SIZE-1:0]};
        MBOffset <= {{(64-`KB_SIZE-`MB_SIZE){1'b0}}, cpu_request.addr[`KB_SIZE+`MB_SIZE-1:0]};
        KBOffset <= {{(64-`KB_SIZE){1'b0}}, cpu_request.addr[`KB_SIZE-1:0]};
    end

    logic unsigned[8:0] TB1Entry;
    logic unsigned[8:0] TB0Entry;

    // TODO: Double check these values!
    always @* begin
        TB1Entry <= GBAddr >> (`KB_SIZE+`MB_SIZE+`GB_SIZE);
        TB0Entry <= MBAddr >> (`KB_SIZE+`MB_SIZE);
    end

    logic passResult;

    // Pass through memory
    always @* begin
        if (!enabled) begin
            cpu_exception <= NONE;

            mem_request <= cpu_request;
            passResult <= 1;
            stage <= IDLE;
        end

        if (passResult)
            cpu_result <= mem_result;
        else
            cpu_result <= {64'b0, 1'b0};
    end

    // Don't pass if cpu_exception is not NONE
    always @* begin
        if (cpu_exception != NONE)
            cpu_result <= {64'b0, 1'b0};
    end

    logic foundEntry;

    // IDLE
    always @(posedge clock) begin
        foundEntry = 0;

        if (
            enabled &&
            cpu_request.isValid &&
            (stage == IDLE)
        ) begin
            cpu_exception = NONE;

            for (i = 0; i < TLBEntries; i = i + 1) begin
                // GB entry lookup
                if (
                    (buffer[i].virtualAddr == GBAddr) &&
                    (buffer[i].size == `GB) &&
                    buffer[i].isValid
                ) begin
                    foundEntry = 1;
                    
                    if (buffer[i].isPrivaliged && !cpu_request.isPrivaliged)
                        cpu_exception <= PAGE_PRIVALIGED_ACCESS;

                    else if (!buffer[i].canWrite && cpu_request.isWrite)
                        cpu_exception <= PAGE_READ_ONLY;
                    
                    else begin
                        mem_request <= {
                            buffer[i].physicalAddr | GBOffset,
                            cpu_request.data,
                            cpu_request.isWrite,
                            1'b0,
                            1'b1
                        };

                        passResult <= 1;
                    end

                // MB entry lookup
                end else if (
                    (buffer[i].virtualAddr == MBAddr) &&
                    (buffer[i].size == `MB) &&
                    buffer[i].isValid
                ) begin
                    foundEntry = 1;

                    if (buffer[i].isPrivaliged && !cpu_request.isPrivaliged)
                        cpu_exception <= PAGE_PRIVALIGED_ACCESS;

                    else if (!buffer[i].canWrite && cpu_request.isWrite)
                        cpu_exception <= PAGE_READ_ONLY;
                    
                    else begin
                        mem_request <= {
                            buffer[i].physicalAddr | MBOffset,
                            cpu_request.data,
                            cpu_request.isWrite,
                            1'b0,
                            1'b1
                        };

                        passResult <= 1;
                    end
                
                // KB entry lookup
                end else if (
                    (buffer[i].virtualAddr == KBAddr) &&
                    (buffer[i].size == `KB) &&
                    buffer[i].isValid
                ) begin
                    foundEntry = 1;

                    if (buffer[i].isPrivaliged && !cpu_request.isPrivaliged)
                        cpu_exception <= PAGE_PRIVALIGED_ACCESS;

                    else if (!buffer[i].canWrite && cpu_request.isWrite)
                        cpu_exception <= PAGE_READ_ONLY;
                    
                    else begin
                        mem_request <= {
                            buffer[i].physicalAddr | KBOffset,
                            cpu_request.data,
                            cpu_request.isWrite,
                            1'b0,
                            1'b1
                        };

                        passResult <= 1;
                    end
                end
            end

            // Page Table lookup
            if (!foundEntry) begin
                mem_request <= {
                    pageTableAddr | {TB1Entry, 3'b0},
                    64'b0,
                    1'b0,
                    1'b0,
                    1'b1
                };

                passResult <= 0;
                stage <= LOOKUP_PT0;
            end
        end
    end

    // Lookup PT0
    always @(posedge clock) begin
        if (
            enabled &&
            (stage == LOOKUP_PT0) &&
            (mem_result.isValid)
        ) begin
            if (mem_result.data & `PAGE_FLAG_PRESENT) begin
                if (mem_result.data & `PAGE_FLAG_SIZE) begin
                    // GB page
                    buffer[counter] <= {
                        GBAddr,
                        {mem_result.data[63:`KB_SIZE], {(`KB_SIZE){1'b0}}},
                        2'h`GB,
                        (mem_result.data & `PAGE_FLAG_PRIVALIGE) ? 1'b1 : 1'b0,
                        (mem_result.data & `PAGE_FLAG_WRITE) ? 1'b1 : 1'b0,
                        1'b1
                    };

                    counter <= counter + 1;
                    stage <= IDLE;

                end else begin
                    mem_request <= {
                        {mem_result.data[63:`KB_SIZE], {(`KB_SIZE){1'b0}}} | {TB0Entry, 3'b0},
                        64'b0,
                        1'b0,
                        1'b0,
                        1'b1
                    };

                    stage <= LOOKUP_PT1;
                end

            end else begin
                stage <= IDLE;
                cpu_exception <= NO_PAGE_MAPPED;

            end
        end
    end

    // Lookup PT1
    always @(posedge clock) begin
        if (
            enabled &&
            (stage == LOOKUP_PT1) &&
            (mem_result.isValid)
        ) begin
            if (mem_result.data & `PAGE_FLAG_PRESENT) begin
                if (mem_result.data & `PAGE_FLAG_SIZE) begin
                    // MB page
                    buffer[counter] <= {
                        MBAddr,
                        {mem_result.data[63:`KB_SIZE], {(`KB_SIZE){1'b0}}},
                        2'h`MB,
                        (mem_result.data & `PAGE_FLAG_PRIVALIGE) != 0,
                        (mem_result.data & `PAGE_FLAG_WRITE) != 0,
                        1'b1
                    };

                    counter <= counter + 1;
                    stage <= IDLE;

                end else begin
                    mem_request <= {
                        {mem_result.data[63:`KB_SIZE], {(`KB_SIZE){1'b0}}} | {TB0Entry, 3'b0},
                        64'b0,
                        1'b0,
                        1'b0,
                        1'b1
                    };

                    stage <= LOOKUP_PT2;
                end

            end else begin
                stage <= IDLE;
                cpu_exception <= NO_PAGE_MAPPED;

            end
        end
    end

    // Lookup PT2
    always @(posedge clock) begin
        if (
            enabled &&
            (stage == LOOKUP_PT2) &&
            (mem_result.isValid)
        ) begin
            if (mem_result.data & `PAGE_FLAG_PRESENT) begin
                if (mem_result.data & `PAGE_FLAG_SIZE) begin
                    // KB page
                    buffer[counter] <= {
                        KBAddr,
                        {mem_result.data[63:`KB_SIZE], {(`KB_SIZE){1'b0}}},
                        2'h`KB,
                        (mem_result.data & `PAGE_FLAG_PRIVALIGE) != 0,
                        (mem_result.data & `PAGE_FLAG_WRITE) != 0,
                        1'b1
                    };

                    counter <= counter + 1;
                    stage <= IDLE;

                end else begin
                    stage <= IDLE;
                    cpu_exception <= NO_PAGE_MAPPED;
                end

            end else begin
                stage <= IDLE;
                cpu_exception <= NO_PAGE_MAPPED;

            end
        end
    end
    
    ulong_t addr, phys;
    PageSize psize;
    logic isPri, canWri, isVal;

    always @* begin
        addr <= buffer[3].virtualAddr;
        phys <= buffer[3].physicalAddr;
        psize <= buffer[3].size;
        isPri <= buffer[3].isPrivaliged;
        canWri <= buffer[3].canWrite;
        isVal <= buffer[3].isValid;
    end

endmodule

tests/mmu/testbench.sv
`include "tests/testing.svh"

`include "rtl/types.svh"
`include "rtl/requests.svh"
`include "rtl/exceptions.svh"

import types::*;
import requests::*;
import exceptions::*;


module MMUTest();
    parameter MMUTLBEntries = 16;
    parameter RAMSize = 16;

    logic clock, reset;
    logic enabled;

    ulong_t pageTableAddr;

    cpuMemRequest_t cpu_request;
    cpuMemResult_t cpu_result;
    exception_t cpu_exception;

    cpuMemRequest_t mem_request;
    cpuMemResult_t mem_result;

    ubyte_t RAM[RAMSize*'h1000-1:0];

    MMU mmu(
        clock, reset,
        enabled,
        pageTableAddr,
        cpu_request,
        cpu_result,
        cpu_exception,
        mem_request,
        mem_result
    );

    defparam mmu.TLBEntries = MMUTLBEntries;

    int i;

    initial begin
        clock = 0;
        reset = 1;

        enabled = 0;

        pageTableAddr = 64'h0;

        cpu_request = {64'h0, 64'h0, 1'b0, 1'b0, 1'b0};
        mem_result = {64'h0, 1'b0};

        $readmemh({`PATH, "memory.hex"}, RAM);
    end

    initial begin
        $dumpfile(`DUMP_FILE);
        $dumpvars();
        #1
        reset = 0;

        #3

        
        `DO_TEST(cpu_result, {64'h0, 1'b0}, "Paging disabled; Idle");
        `DO_TEST(cpu_exception, NONE, "Pagine disabled; Idle - exception");

        enabled = 1;

        #2
        `DO_TEST(cpu_request, {64'h0, 1'b0}, "Paging enabled; Idle");
        `DO_TEST(cpu_exception, NONE, "Pagine enabled; Idle - exception");

        enabled = 0;

        cpu_request = {64'h50, 64'habcd, 1'b1, 1'b0, 1'b1};

        #6
        `DO_TEST(cpu_result, {64'h0, 1'b1}, "Paging disabled; Write");
        `DO_TEST(cpu_exception, NONE, "Pagine disabled; Write - exception");

        cpu_request = {64'h50, 64'h0, 1'b0, 1'b0, 1'b1};

        #6
        `DO_TEST(cpu_result, {64'habcd, 1'b1}, "Paging disabled; Read");
        `DO_TEST(cpu_exception, NONE, "Pagine disabled; Read - exception");

        cpu_request = {64'h50, 64'habcd, 1'b1, 1'b1, 1'b1};

        #6
        `DO_TEST(cpu_result, {64'h0, 1'b1}, "Paging disabled; Write privaliged");
        `DO_TEST(cpu_exception, NONE, "Pagine disabled; Write privaliged - exception");

        cpu_request = {64'h50, 64'h0, 1'b0, 1'b1, 1'b1};

        #6
        `DO_TEST(cpu_result, {64'habcd, 1'b1}, "Paging disabled; Read privaliged");
        `DO_TEST(cpu_exception, NONE, "Pagine disabled; Read privaliged - exception");

        cpu_request = {64'h0, 64'b0, 1'b0, 1'b0, 1'b0};

        pageTableAddr = 64'h1000;

        #2
        `DO_TEST(cpu_exception, NONE, "Paging disabled; Page table addr - exception");

        enabled = 1;
        
        #2
        `DO_TEST(cpu_exception, NONE, "Paging enabled; Page table addr - exception");

        #2
        pageTableAddr = 0;

        cpu_request = {64'h50, 64'h0, 1'b0, 1'b0, 1'b1};

        #12
        `DO_TEST(cpu_result, {64'habcd, 1'b1}, "Paging enabled; Page read");
        `DO_TEST(cpu_exception, NONE, "Paging enabled; - exception");

        cpu_request = {64'h50, 64'h1, 1'b1, 1'b0, 1'b1};

        #6
        `DO_TEST(cpu_result, {64'b0, 1'b0}, "Paging enabled; Write to R/O");
        `DO_TEST(cpu_exception, PAGE_READ_ONLY, "Paging enabled; Write to R/O - exception");

        cpu_request = {64'h50, 64'h1, 1'b0, 1'b1, 1'b1};

        #6
        `DO_TEST(cpu_result, {64'habcd, 1'b1}, "Paging enabled; Privileged read");
        `DO_TEST(cpu_exception, NONE, "Paging enabled; Privileged read - exception");

        cpu_request = {64'h50, 64'h1, 1'b1, 1'b1, 1'b1};

        #6
        `DO_TEST(cpu_result, {64'b0, 1'b0}, "Paging enabled; Privileged write to R/O");
        `DO_TEST(cpu_exception, PAGE_READ_ONLY, "Paging enabled; Privileged write to R/O - exception");

        cpu_request = {64'h40000080, 64'b0, 1'b0, 1'b0, 1'b1};

        #12
        `DO_TEST(cpu_result, {64'b0, 1'b1}, "Paging enabled; GB page read");
        `DO_TEST(cpu_exception, NONE, "Paging enabled; GB page read - exception");

        cpu_request = {64'h40000080, 64'b1, 1'b1, 1'b0, 1'b1};

        #6
        `DO_TEST(cpu_result, {64'b0, 1'b0}, "Paging enabled; GB page write");
        `DO_TEST(cpu_exception, PAGE_READ_ONLY, "Paging enabled; GB page write - exception");

        cpu_request = {64'h40000080, 64'b0, 1'b0, 1'b1, 1'b1};

        #6
        `DO_TEST(cpu_result, {64'b0, 1'b1}, "Paging enabled; Privileged GB page read");
        `DO_TEST(cpu_exception, NONE, "Paging enabled; Privileged GB page read - exception");

        cpu_request = {64'h40000080, 64'b1, 1'b1, 1'b1, 1'b1};

        #6
        `DO_TEST(cpu_result, {64'b0, 1'b0}, "Paging enabled; Privileged GB page write");
        `DO_TEST(cpu_exception, PAGE_READ_ONLY, "Paging enabled; Privileged GB page write - exception");

        cpu_request = {64'h80000060, 64'b0, 1'b0, 1'b0, 1'b1};

        #12
        `DO_TEST(cpu_result, {64'b0, 1'b1}, "Paging enabled; Write-enabled page read");
        `DO_TEST(cpu_exception, NONE, "Paging enabled; Write-enabled page read - exception");

        cpu_request = {64'h80000060, 64'b1, 1'b1, 1'b0, 1'b1};

        #6
        `DO_TEST(cpu_result, {64'b0, 1'b1}, "Paging enabled; Write-enable page write");
        `DO_TEST(cpu_exception, NONE, "Paging enabled; Write-enable page write - exception");

        cpu_request = {64'h80000060, 64'b0, 1'b0, 1'b0, 1'b1};

        #6
        `DO_TEST(cpu_result, {64'b1, 1'b1}, "Paging enabled; Write-enable page read");
        `DO_TEST(cpu_exception, NONE, "Paging enabled; Write-enable page read - exception");
        
        cpu_request = {64'h80000060, 64'h2, 1'b1, 1'b1, 1'b1};

        #6
        `DO_TEST(cpu_result, {64'b0, 1'b1}, "Paging enabled; Privileged write-enable page write");
        `DO_TEST(cpu_exception, NONE, "Paging enabled; Privileged write-enable page write - exception");

        cpu_request = {64'h80000060, 64'b0, 1'b0, 1'b1, 1'b1};

        #6
        `DO_TEST(cpu_result, {64'h2, 1'b1}, "Paging enabled; Privileged write-enable page read");
        `DO_TEST(cpu_exception, NONE, "Paging enabled; Privileged write-enable page read - exception");

        cpu_request = {64'hc0000060, 64'b0, 1'b0, 1'b0, 1'b1};

        #12
        `DO_TEST(cpu_result, {64'b0, 1'b0}, "Paging enabled; Privileged-Page R/O read");
        `DO_TEST(cpu_exception, PAGE_PRIVALIGED_ACCESS, "Paging enabled; Privileged-Page R/O read - exception")

        cpu_request = {64'hc0000060, 64'h3, 1'b1, 1'b0, 1'b1};

        #6
        `DO_TEST(cpu_result, {64'b0, 1'b0}, "Paging enabled; Privileged-Page R/O write");
        `DO_TEST(cpu_exception, PAGE_PRIVALIGED_ACCESS, "Paging enabled; Privileged-Page R/O write - exception");


        cpu_request = {64'hc0000060, 64'b0, 1'b0, 1'b1, 1'b1};

        #6
        `DO_TEST(cpu_result, {64'h2, 1'b1}, "Paging enabled; Privileged Privileged-Page R/O read");
        `DO_TEST(cpu_exception, NONE, "Paging enabled; Privileged Privileged-Page R/O read - exception")

        cpu_request = {64'hc0000060, 64'h3, 1'b1, 1'b1, 1'b1};

        #6
        `DO_TEST(cpu_result, {64'b0, 1'b0}, "Paging enabled; Privileged Privileged-Page R/O write");
        `DO_TEST(cpu_exception, PAGE_READ_ONLY, "Paging enabled; Privileged Privileged-Page R/O write - exception");

        cpu_request = {64'h100000060, 64'h0, 1'b0, 1'b0, 1'b1};

        #12
        `DO_TEST(cpu_result, {64'h0, 1'b0}, "Paging enabled; Privileged-Page write-enabled read");
        `DO_TEST(cpu_exception, PAGE_PRIVALIGED_ACCESS, "Paging enabled; Privileged-Page write-enabled read - exception")

        cpu_request = {64'h100000060, 64'h3, 1'b1, 1'b0, 1'b1};

        #6
        `DO_TEST(cpu_result, {64'b0, 1'b0}, "Paging enabled; Privileged-Page write-enabled write");
        `DO_TEST(cpu_exception, PAGE_PRIVALIGED_ACCESS, "Paging enabled; Privileged-Page write-enabled write - exception");

        cpu_request = {64'h100000060, 64'h0, 1'b0, 1'b1, 1'b1};

        #6
        `DO_TEST(cpu_result, {64'h2, 1'b1}, "Paging enabled; Privileged Privileged-Page write-enabled read");
        `DO_TEST(cpu_exception, NONE, "Paging enabled; Privileged Privileged-Page write-enabled read - exception")

        cpu_request = {64'h100000060, 64'h3, 1'b1, 1'b1, 1'b1};

        #6
        `DO_TEST(cpu_result, {64'b0, 1'b1}, "Paging enabled; Privileged Privileged-Page write-enabled write");
        `DO_TEST(cpu_exception, NONE, "Paging enabled; Privileged Privileged-Page write-enabled write - exception");

        cpu_request = {64'h100000060, 64'h0, 1'b0, 1'b1, 1'b1};

        #6
        `DO_TEST(cpu_result, {64'h3, 1'b1}, "Paging enabled; Privileged Privileged-Page write-enabled write test");
        `DO_TEST(cpu_exception, NONE, "Paging enabled; Privileged Privileged-Page write-enabled read test - exception")

        #16
        $finish();
    end

    always begin
        #1 clock = !clock;

        if (clock) begin
            if (mem_request.isValid) begin
                if (mem_request.isWrite) begin
                    {
                        RAM[mem_request.addr],
                        RAM[mem_request.addr+1],
                        RAM[mem_request.addr+2],
                        RAM[mem_request.addr+3],
                        RAM[mem_request.addr+4],
                        RAM[mem_request.addr+5],
                        RAM[mem_request.addr+6],
                        RAM[mem_request.addr+7]
                    } = mem_request.data;

                    mem_result = {64'h0, 1'b1};

                    $display("[%0d] Writing to %0h: %h", $realtime, mem_request.addr, mem_request.data);
                end else begin
                    mem_result = {
                        {
                            RAM[mem_request.addr],
                            RAM[mem_request.addr+1],
                            RAM[mem_request.addr+2],
                            RAM[mem_request.addr+3],
                            RAM[mem_request.addr+4],
                            RAM[mem_request.addr+5],
                            RAM[mem_request.addr+6],
                            RAM[mem_request.addr+7]
                        },
                        1'b1
                    };

                    $display("[%0d] Reading from %0h: %h", $realtime, mem_request.addr, mem_result.data);
                end
            end
        end
    end

endmodule

tests/mmu/testbench.vcd
$date
	Wed Apr 21 22:20:08 2021
$end
$version
	Icarus Verilog
$end
$timescale
	1s
$end
$scope module MMUTest $end
$var wire 131 ! mem_request [130:0] $end
$var wire 65 " cpu_result [64:0] $end
$var wire 8 # cpu_exception [7:0] $end
$var reg 1 $ clock $end
$var reg 131 % cpu_request [130:0] $end
$var reg 1 & enabled $end
$var reg 65 ' mem_result [64:0] $end
$var reg 64 ( pageTableAddr [63:0] $end
$var reg 1 ) reset $end
$scope module mmu $end
$var wire 1 $ clock $end
$var wire 131 * cpu_request [130:0] $end
$var wire 1 & enabled $end
$var wire 65 + mem_result [64:0] $end
$var wire 64 , pageTableAddr [63:0] $end
$var wire 1 ) reset $end
$var reg 64 - GBAddr [63:0] $end
$var reg 64 . GBOffset [63:0] $end
$var reg 64 / KBAddr [63:0] $end
$var reg 64 0 KBOffset [63:0] $end
$var reg 64 1 MBAddr [63:0] $end
$var reg 64 2 MBOffset [63:0] $end
$var reg 9 3 TB0Entry [8:0] $end
$var reg 9 4 TB1Entry [8:0] $end
$var reg 64 5 addr [63:0] $end
$var reg 2128 6 buffer [2127:0] $end
$var reg 1 7 canWri $end
$var reg 4 8 counter [3:0] $end
$var reg 8 9 cpu_exception [7:0] $end
$var reg 65 : cpu_result [64:0] $end
$var reg 1 ; foundEntry $end
$var reg 1 < isPri $end
$var reg 1 = isVal $end
$var reg 131 > mem_request [130:0] $end
$var reg 1 ? passResult $end
$var reg 64 @ phys [63:0] $end
$var reg 2 A psize [1:0] $end
$var reg 2 B stage [1:0] $end
$var integer 32 C i [31:0] $end
$upscope $end
$upscope $end
$enddefinitions $end
#0
$dumpvars
b10000 C
b0 B
b0 A
b0 @
1?
b0 >
0=
0<
0;
b0 :
b0 9
b0 8
07
b0 6
b0 5
b0 4
b0 3
b0 2
b0 1
b0 0
b0 /
b0 .
b0 -
b0 ,
b0 +
b0 *
1)
b0 (
b0 '
0&
b0 %
0$
b0 #
b0 "
b0 !
$end
#1
1$
0)
#2
0$
#3
1$
#4
0$
1&
#5
1$
#6
b1010000 0
b1010000 2
b1010000 .
b10100000000000000000000000000000000000000000000000000001010101111001101101 !
b10100000000000000000000000000000000000000000000000000001010101111001101101 >
0$
b10100000000000000000000000000000000000000000000000000001010101111001101101 %
b10100000000000000000000000000000000000000000000000000001010101111001101101 *
0&
#7
b1 "
b1 :
b1 '
b1 +
1$
#8
0$
#9
1$
#10
0$
#11
1$
#12
b10100000000000000000000000000000000000000000000000000000000000000000000001 !
b10100000000000000000000000000000000000000000000000000000000000000000000001 >
0$
b10100000000000000000000000000000000000000000000000000000000000000000000001 %
b10100000000000000000000000000000000000000000000000000000000000000000000001 *
#13
b10101011110011011 "
b10101011110011011 :
b10101011110011011 '
b10101011110011011 +
1$
#14
0$
#15
1$
#16
0$
#17
1$
#18
b10100000000000000000000000000000000000000000000000000001010101111001101111 !
b10100000000000000000000000000000000000000000000000000001010101111001101111 >
0$
b10100000000000000000000000000000000000000000000000000001010101111001101111 %
b10100000000000000000000000000000000000000000000000000001010101111001101111 *
#19
b1 "
b1 :
b1 '
b1 +
1$
#20
0$
#21
1$
#22
0$
#23
1$
#24
b10100000000000000000000000000000000000000000000000000000000000000000000011 !
b10100000000000000000000000000000000000000000000000000000000000000000000011 >
0$
b10100000000000000000000000000000000000000000000000000000000000000000000011 %
b10100000000000000000000000000000000000000000000000000000000000000000000011 *
#25
b10101011110011011 "
b10101011110011011 :
b10101011110011011 '
b10101011110011011 +
1$
#26
0$
#27
1$
#28
0$
#29
1$
#30
b0 !
b0 >
b0 0
b0 2
b0 .
0$
b1000000000000 (
b1000000000000 ,
b0 %
b0 *
#31
1$
#32
0$
1&
#33
1$
#34
0$
#35
1$
#36
b1010000 0
b1010000 2
b1010000 .
0$
b10100000000000000000000000000000000000000000000000000000000000000000000001 %
b10100000000000000000000000000000000000000000000000000000000000000000000001 *
b0 (
b0 ,
#37
b0 "
b0 :
b1 B
0?
b1 !
b1 >
b10000 C
1$
#38
0$
#39
b10 B
b10000000000000000000000000000000000000000000000000000000000000000000000000000001 !
b10000000000000000000000000000000000000000000000000000000000000000000000000000001 >
b10000000000011 '
b10000000000011 +
1$
#40
0$
#41
b11 B
b100000000000000000000000000000000000000000000000000000000000000000000000000000001 !
b100000000000000000000000000000000000000000000000000000000000000000000000000000001 >
b100000000000011 '
b100000000000011 +
1$
#42
0$
#43
b0 B
b1 8
b11000000000000000000000000000000000000000000000000001 6
b1100000000000000000000000000000000000000000000111 '
b1100000000000000000000000000000000000000000000111 +
1$
#44
0$
#45
b1100000000000000000000000000000000000000000000111 "
b1100000000000000000000000000000000000000000000111 :
1?
b1100000000000000000000000000000000000000010100000000000000000000000000000000000000000000000000000000000000000000001 !
b1100000000000000000000000000000000000000010100000000000000000000000000000000000000000000000000000000000000000000001 >
1;
b10000 C
1$
#46
0$
#47
b10101011110011011 "
b10101011110011011 :
b10000 C
1;
b10101011110011011 '
b10101011110011011 +
1$
#48
0$
b10100000000000000000000000000000000000000000000000000000000000000000001101 %
b10100000000000000000000000000000000000000000000000000000000000000000001101 *
#49
b0 "
b0 :
b10 #
b10 9
b10000 C
1;
1$
#50
0$
#51
b10000 C
b10 #
b10 9
1;
1$
#52
0$
#53
b10000 C
b10 #
b10 9
1;
1$
#54
b10101011110011011 "
b10101011110011011 :
0$
b10100000000000000000000000000000000000000000000000000000000000000000001011 %
b10100000000000000000000000000000000000000000000000000000000000000000001011 *
#55
b1100000000000000000000000000000000000000010100000000000000000000000000000000000000000000000000000000000000000001001 !
b1100000000000000000000000000000000000000010100000000000000000000000000000000000000000000000000000000000000000001001 >
b10000 C
b0 #
b0 9
1;
1$
#56
0$
#57
b10000 C
1;
1$
#58
0$
#59
b10000 C
1;
1$
#60
0$
b10100000000000000000000000000000000000000000000000000000000000000000001111 %
b10100000000000000000000000000000000000000000000000000000000000000000001111 *
#61
b0 "
b0 :
b10 #
b10 9
b10000 C
1;
1$
#62
0$
#63
b10000 C
b10 #
b10 9
1;
1$
#64
0$
#65
b10000 C
b10 #
b10 9
1;
1$
#66
b1 4
b10101011110011011 "
b10101011110011011 :
b10000000 0
b10000000 2
b10000000 .
b1000000000000000000000000000000 /
b1000000000000000000000000000000 1
b1000000000000000000000000000000 -
0$
b10000000000000000000000100000000000000000000000000000000000000000000000000000000000000000000000001 %
b10000000000000000000000100000000000000000000000000000000000000000000000000000000000000000000000001 *
#67
b0 "
b0 :
b1 B
0?
b10000000000000000000000000000000000000000000000000000000000000000000001 !
b10000000000000000000000000000000000000000000000000000000000000000000001 >
b10000 C
b0 #
b0 9
0;
1$
#68
0$
#69
b0 B
b10 8
b10000000000000000000000000000000000000000000000000000000000000000000000000000000000000000000000100010000000000000000000000000000000000000000000000000000000000000000000000000000000011000000000000000000000000000000000000000000000000001 6
b111 '
b111 +
1$
#70
0$
#71
b111 "
b111 :
1?
b100000000000000000000000000000000000000000000000000000000000000000000000001 !
b100000000000000000000000000000000000000000000000000000000000000000000000001 >
1;
b10000 C
1$
#72
0$
#73
b1 "
b1 :
b10000 C
1;
b1 '
b1 +
1$
#74
0$
#75
b10000 C
1;
1$
#76
0$
#77
b10000 C
1;
1$
#78
0$
b10000000000000000000000100000000000000000000000000000000000000000000000000000000000000000000001101 %
b10000000000000000000000100000000000000000000000000000000000000000000000000000000000000000000001101 *
#79
b0 "
b0 :
b10 #
b10 9
b10000 C
1;
1$
#80
0$
#81
b10000 C
b10 #
b10 9
1;
1$
#82
0$
#83
b10000 C
b10 #
b10 9
1;
1$
#84
b1 "
b1 :
0$
b10000000000000000000000100000000000000000000000000000000000000000000000000000000000000000000000011 %
b10000000000000000000000100000000000000000000000000000000000000000000000000000000000000000000000011 *
#85
b10000 C
b0 #
b0 9
1;
1$
#86
0$
#87
b10000 C
1;
1$
#88
0$
#89
b10000 C
1;
1$
#90
0$
b10000000000000000000000100000000000000000000000000000000000000000000000000000000000000000000001111 %
b10000000000000000000000100000000000000000000000000000000000000000000000000000000000000000000001111 *
#91
b0 "
b0 :
b10 #
b10 9
b10000 C
1;
1$
#92
0$
#93
b10000 C
b10 #
b10 9
1;
1$
#94
0$
#95
b10000 C
b10 #
b10 9
1;
1$
#96
b10 4
b1 "
b1 :
b1100000 0
b1100000 2
b1100000 .
b10000000000000000000000000000000 /
b10000000000000000000000000000000 1
b10000000000000000000000000000000 -
0$
b100000000000000000000000011000000000000000000000000000000000000000000000000000000000000000000000001 %
b100000000000000000000000011000000000000000000000000000000000000000000000000000000000000000000000001 *
#97
b0 "
b0 :
b1 B
0?
b100000000000000000000000000000000000000000000000000000000000000000000001 !
b100000000000000000000000000000000000000000000000000000000000000000000001 >
b10000 C
b0 #
b0 9
0;
1$
#98
0$
