rtl/instructions.svh
`ifndef CPU_INSTRUCTIONS
`define CPU_INSTRUCTIONS

`include "rtl/types.svh"
import types::*;

package instructions;

typedef enum logic[15:0] {

    NOP,
    HALT,

    LOADMCR,
    STOREMCR,
    
    SYSCALL,
    SYSRET,
    INT,
    INTRET,

    ADD,
    SUB,
    MUL,

    UDIV,
    UMOD,

    SDIV,
    SMOD,

    INC,
    DEC,

    FADD,
    FSUB,
    FMUL,
    FDIV,
    FMOD,
    FFMA,

    FEPOW, // e ^ x
    F2POW, // 2 ^ x
    F10POW, // 10 ^ x
    FEPOW1, // e ^ x - 1
    F2POW1, // 2 ^ x - 1
    F10POW1, // 10 ^ x - 1

    FLN, // ln(x)
    F2LOG, // log2(x)
    F10LOG, // log10(x)
    FLN1, // ln(x + 1)
    F2LOG1, // log2(x + 1)
    F10LOG1, // log10(x + 1)

    FDISTANCE, // sqrt(x ^ 2 + y ^ 2)

    FSQRT,

    FPOW1, // (1 + x) ^ y
    FFPOW, // x ^ (1 / y)
    FPOW, // x ^ y
    
    FSIN,
    FCOS,
    FTAN,

    FASIN, // arcsin(x)
    FACOS, // arccos(x)
    FATAN, // arctan(x)
    FATAN2, // atan2(x, y)

    FSINPI, // sin(PI * x)
    FCOSPI, // cos(PI * x)
    FTANPI, // tan(PI * x)

    FASINPI, // arcsin(x) / PI
    FACOSPI, // arccos(x) / PI
    FATANPI, // arctan(x) / PI
    FATAN2PI, // atan2(x, y) / PI

    FSINH, // sinh(x)
    FCOSH, // cosh(x)
    FTANH, // tanh(x)

    FARSINH, // arsinh(x)
    FARCOSH, // arcosh(x)
    FARTANH, // artanh(x)

    FABS,
    FNEG,
    FCOPY,
    FTEST,

    TOINT,
    TOFLOAT,

    AND,
    OR,
    XOR,
    NOT,
    ROLR,
    ROLL,
    SHIFTR,
    SHIFTL,
    FLIP,

    SWAP,
    MOVE,

    CMP,

    JMP,
    BRA,
    RET,

    LOAD,
    STORE,
    STOREIF, // Only stores if value matches

    PUSH,
    POP,

    BIT,

    OUT,
    IN,

    SETF,
    CLEARF

} opcode_t;

typedef enum logic[3:0] {
    BITS_8 =   'h0,
    BITS_16 =  'h1,
    BITS_32 =  'h2,
    BITS_64 =  'h3
} sizeFlags_t;

typedef logic[7:0] flags_t;

`define NO_FLAGS 0

`define USE_ARG0_AS_IMMIDIATE (1<<0)
`define USE_ARG1_AS_IMMIDIATE (1<<1)
`define USE_ARG2_AS_IMMIDIATE (1<<2)
`define USE_ARG3_AS_IMMIDIATE (1<<3)

`define IS_FLOAT_NAN (1<<1)
`define IS_FLOAT_POS_NAN (1<<2)
`define IS_FLOAT_NEG_NAN (1<<3)
`define IS_FLOAT_INF (1<<4)
`define IS_FLOAT_POS_INF (1<<5)
`define IS_FLOAT_NEG_INF (1<<6)

`define ROUND_TO_NEAREST_EVEN (1<<2)
`define ROUND_TO_NEAREST_ZERO (1<<3)
`define ROUND_TO_ZERO (1<<4)
`define ROUND_TO_INF (1<<5)
`define ROUND_TO_NEG_INF (1<<6)

`define USE_CARRY_BIT (1<<2)

`define IS_RELATIVE (1<<4)

`define IS_ATOMIC (1<<4)

`define BIT_SET (1<<2)
`define BIT_CLEAR (1<<3)
`define BIT_TEST (1<<4)

`define SELECT_C_FLAG (1<<2)
`define SELECT_N_FLAG (1<<3)
`define SELECT_Z_FLAG (1<<4)

`define ARG0_SIGN_EXTEND (1<<4)
`define ARG1_SIGN_EXTEND (1<<5)
`define ARG2_SIGN_EXTEND (1<<6)
`define ARG3_SIGN_EXTEND (1<<7)

`define BRANCH_SIGNED (1<<0)
`define BRANCH_C (1<<1)
`define BRANCH_N (1<<2)
`define BRANCH_Z (1<<3)

`define BRANCH_NOT_C (1<<4)
`define BRANCH_NOT_N (1<<5)
`define BRANCH_NOT_z (1<<6)

typedef struct packed {
    opcode_t opcode;
    sizeFlags_t argSize0, argSize1, argSize2, argSize3;
    flags_t flags;
    ulong_t arg0, arg1, arg2, arg3;
} instruction_t;

endpackage

`endif

rtl/types.svh
`ifndef CPU_TYPES
`define CPU_TYPES

package types;

typedef logic signed[7:0] byte_t;
typedef logic signed[15:0] short_t;
typedef logic signed[31:0] int_t;
typedef logic signed[63:0] long_t;

typedef logic unsigned[7:0] ubyte_t;
typedef logic unsigned[15:0] ushort_t;
typedef logic unsigned[31:0] uint_t;
typedef logic unsigned[63:0] ulong_t;

typedef struct packed {
    logic sign;
    logic[4:0] exponent;
    logic[9:0] fraction;
} half_t;

typedef struct packed {
    logic sign;
    logic[7:0] exponent;
    logic[22:0] fraction;
} single_t;

typedef struct packed {
    logic sign;
    logic[10:0] exponent;
    logic[51:0] fraction;
} double_t;

typedef enum logic[1:0] {
    HALF,
    SINGLE,
    DOUBLE
} floatType_t;

typedef union packed {
    half_t half;
    single_t single;
    double_t double;
} floatValue_t;

typedef struct packed {
    floatType_t ftype;
    floatValue_t value;
} float_t;

endpackage

`endif

rtl/alu/value.sv
`include "rtl/types.svh"
`include "rtl/instructions.svh"

import types::*;
import instructions::*;

module IValue(
    input ulong_t in,
    output ulong_t out,

    input sizeFlags_t size,
    input logic signExtend
);

    always @* begin
        case (size)
            BITS_8: begin
                if (signExtend)
                    out <= {{56{in[7]}}, in[7:0]};
                else
                    out <= {56'b0, in[7:0]};
            end
            BITS_16: begin
                if (signExtend)
                    out <= {{48{in[15]}}, in[15:0]};
                else
                    out <= {48'b0, in[15:0]};
            end
            BITS_32: begin
                if (signExtend)
                    out <= {{32{in[31]}}, in[31:0]};
                else
                    out <= {32'b0, in[31:0]};
            end
            BITS_64:
                out <= in;
        endcase
    end

endmodule

rtl/alu/compare.sv
`include "rtl/types.svh"

import types::*;

module ICompare(
    input ulong_t a, b,

    output logic zero, negitive
);
    ulong_t result;

    // Sign extend / Zero extend
    always @* begin
        result <= a - b;

        zero <= result == 0;
        negitive <= result[63];
    end

endmodule

tests/testing.svh
`ifndef TESTING
`define TESTING

`define DO_TEST(value, expected, name) \
if (value == expected) \
    $display("Passed (%s, %0d [%0d]): %s", `__FILE__, `__LINE__, $realtime, name); \
else \
    $display("Failed (%s, %0d [%0d]): %s", `__FILE__, `__LINE__, $realtime, name);

`endif

rtl/alu/arithmetic.sv
`include "rtl/types.svh"
`include "rtl/instructions.svh"

import types::*;
import instructions::*;

module Arithmetic(
    input opcode_t op,
    
    input logic carryIn,

    input ulong_t a, b,
    output ulong_t result,

    output logic divByZero,

    output logic zero, carry, negitive
);

    long_t sa, sb;

    always @* begin
        sa <= a;
        sb <= b;

        zero <= result == 0;
        negitive <= result[63];

        divByZero <=
            ((op == SDIV) || (op == UDIV) || (op == SMOD) || (op == UMOD)) &&
            b == 0;

        case (op)
            ADD: {carry, result} <= a + b + carryIn;
            SUB: {carry, result} <= a - b - carryIn;
            MUL: {carry, result} <= a * b;

            UDIV: {carry, result} <= a / b;
            UMOD: {carry, result} <= a % b;

            SDIV: {carry, result} <= sa / sb;
            SMOD: {carry, result} <= sa % sb;

            INC: {carry, result} <= a + 1;
            DEC: {carry, result} <= a - 1;
        endcase
    end

endmodule

tests/alu/arithmetic.sv
`include "tests/testing.svh"

`include "rtl/types.svh"
`include "rtl/instructions.svh"

`define RESULT_FLAG_CHECK(r, z, c, n, d, msg) \
    `DO_TEST(result, r, {msg, "; resolves correctly"}); \
    `DO_TEST(zero, z, {msg, "; zero flag is correct"}); \
    `DO_TEST(carry, c, {msg, "; carry flag is correct"}); \
    `DO_TEST(negitive, n, {msg, "; negitive flag is correct"}); \
    `DO_TEST(divByZero, d, {msg, "; divide by zero is correct"});

import types::*;
import instructions::*;

module ArithmeticTest();

    opcode_t op;
    logic carryIn;
    ulong_t a, b;
    ulong_t result;
    logic divByZero;
    logic zero, carry, negitive;

    Arithmetic arith(
        op,
        carryIn,
        a, b,
        result,
        divByZero,
        zero, carry, negitive
    );

    initial begin
        op = NOP;
        carryIn = 0;
        a = 0;
        b = 0;
    end

    initial begin
        $dumpfile(`DUMP_FILE);
        $dumpvars();

        op = ADD;
        a = 1;
        b = 2;
        #1
        `RESULT_FLAG_CHECK(3, 0, 0, 0, 0, "1 + 2");

        carryIn = 1;
        #1
        `RESULT_FLAG_CHECK(4, 0, 0, 0, 0, "1 + 2 + carry");

        b = -2;
        carryIn = 0;
        #1
        `RESULT_FLAG_CHECK(-1, 0, 0, 1, 0, "1 + -2");

        carryIn = 1;
        #1
        `RESULT_FLAG_CHECK(0, 1, 1, 0, 0, "1 + -2 + carry");

        a = -1;
        b = 0;
        carryIn = 0;
        #1
        `RESULT_FLAG_CHECK(-1, 0, 0, 1, 0, "-1 + 0");

        carryIn = 1;
        #1
        `RESULT_FLAG_CHECK(0, 1, 1, 0, 0, "-1 + 0 + carry");

        b = 1;
        #1
        `RESULT_FLAG_CHECK(1, 0, 1, 0, 0, "-1 + 1 + carry");

        op = SUB;
        a = 3;
        b = 1;
        carryIn = 0;
        #1
        `RESULT_FLAG_CHECK(2, 0, 0, 0, 0, "3 - 1");

        carryIn = 1;
        #1
        `RESULT_FLAG_CHECK(1, 0, 0, 0, 0, "3 - 1 - carry");

        b = 3;
        #1
        `RESULT_FLAG_CHECK(-1, 0, 1, 1, 0, "3 - 3 - carry");

        carryIn = 0;
        #1
        `RESULT_FLAG_CHECK(0, 1, 0, 0, 0, "3 - 3");

        a = -2;
        b = 1;
        #1
        `RESULT_FLAG_CHECK(-3, 0, 0, 1, 0, "-2 - 1");

        carryIn = 1;
        #1
        `RESULT_FLAG_CHECK(-4, 0, 0, 1, 0, "-2 - 1 - carry");

        b = -2;
        #1
        `RESULT_FLAG_CHECK(-1, 0, 1, 1, 0, "-2 - -2 - carry");

        carryIn = 0;
        #1
        `RESULT_FLAG_CHECK(0, 1, 0, 0, 0, "-2 - -2");

        op = MUL;
        a = 2;
        b = 3;
        #1
        `RESULT_FLAG_CHECK(6, 0, 0, 0, 0, "2 * 3");

        carryIn = 1;
        #1
        `RESULT_FLAG_CHECK(6, 0, 0, 0, 0, "2 * 3 carry");

        b = -1;
        carryIn = 0;
        #1
        `RESULT_FLAG_CHECK(-2, 0, 1, 1, 0, "2 * -1");

        carryIn = 1;
        #1
        `RESULT_FLAG_CHECK(-2, 0, 1, 1, 0, "2 * -1 carry");

        op = UDIV;
        a = 6;
        b = 2;
        #1
        `RESULT_FLAG_CHECK(3, 0, 0, 0, 0, "unsigned 6 / 2");

        carryIn = 0;
        #1
        `RESULT_FLAG_CHECK(3, 0, 0, 0, 0, "unsigned 6 / 3 carry");

        a = -2;
        b = 2;
        #1
        `RESULT_FLAG_CHECK(9223372036854775807, 0, 0, 0, 0, "unsigned -2 / 2");

        carryIn = 1;
        #1
        `RESULT_FLAG_CHECK(9223372036854775807, 0, 0, 0, 0, "unsigned -2 / 2 carry");

        b = -2;
        #1
        `RESULT_FLAG_CHECK(1, 0, 0, 0, 0, "unsigned -2 / -2 carry");

        carryIn = 0;
        #1
        `RESULT_FLAG_CHECK(1, 0, 0, 0, 0, "unsigned -2 / -2");

        b = 0;
        #1
        `DO_TEST(divByZero, 1, "unsigned 0 / 0; divide by zero is correct");

        carryIn = 1;
        #1
        `DO_TEST(divByZero, 1, "unsigned 0 / 0 carry; divide by zero is correct");

        op = SDIV;
        a = 6;
        b = 2;
        #1
        `RESULT_FLAG_CHECK(3, 0, 0, 0, 0, "signed 6 / 2 carry");

        carryIn = 0;
        #1
        `RESULT_FLAG_CHECK(3, 0, 0, 0, 0, "signed 6 / 2");

        b = -2;
        #1
        `RESULT_FLAG_CHECK(-3, 0, 1, 1, 0, "signed 6 / -2");

        carryIn = 1;
        #1
        `RESULT_FLAG_CHECK(-3, 0, 1, 1, 0, "signed 6 / -2 carry");

        b = 0;
        #1
        `DO_TEST(divByZero, 1, "signed 0 / 0 carry; divide by zero is correct");

        carryIn = 0;
        #1
        `DO_TEST(divByZero, 1, "signed 0 / 0; divide by zero is correct");

        op = UMOD;
        a = 2;
        b = 3;
        #1
        `RESULT_FLAG_CHECK(2, 0, 0, 0, 0, "unsigned 2 % 3");

        carryIn = 1;
        #1
        `RESULT_FLAG_CHECK(2, 0, 0, 0, 0, "unsigned 2 % 3 carry");

        a = 4;
        #1
        `RESULT_FLAG_CHECK(1, 0, 0, 0, 0, "unsigned 4 % 3 carry");

        carryIn = 0;
        #1
        `RESULT_FLAG_CHECK(1, 0, 0, 0, 0, "unsigned 4 % 3");

        b = -3;
        #1
        `RESULT_FLAG_CHECK(4, 0, 0, 0, 0, "unsigned 4 % -3");

        carryIn = 1;
        #1
        `RESULT_FLAG_CHECK(4, 0, 0, 0, 0, "unsigned 4 % -3 carry");

        a = -5;
        b = 2;
        #1
        `RESULT_FLAG_CHECK(1, 0, 0, 0, 0, "unsigned -5 % 2 carry");

        carryIn = 0;
        #1
        `RESULT_FLAG_CHECK(1, 0, 0, 0, 0, "unsigned -5 % 2");

        b = 0;
        #1
        `DO_TEST(divByZero, 1, "unsigned 0 % 0; divide by zero is correct");

        carryIn = 1;
        #1
        `DO_TEST(divByZero, 1, "unsigned 0 % 0 carry; divide by zero is correct");

        op = SMOD;
        a = 2;
        b = 3;
        #1
        `RESULT_FLAG_CHECK(2, 0, 0, 0, 0, "signed 2 % 3");

        carryIn = 1;
        #1
        `RESULT_FLAG_CHECK(2, 0, 0, 0, 0, "signed 2 % 3 carry");

        a = 4;
        #1
        `RESULT_FLAG_CHECK(1, 0, 0, 0, 0, "signed 4 % 3 carry");

        carryIn = 0;
        #1
        `RESULT_FLAG_CHECK(1, 0, 0, 0, 0, "signed 4 % 3");

        b = -3;
        #1
        `RESULT_FLAG_CHECK(1, 0, 0, 0, 0, "signed 4 % -3");

        carryIn = 1;
        #1
        `RESULT_FLAG_CHECK(1, 0, 0, 0, 0, "signed 4 % -3 carry");

        a = -5;
        b = 2;
        #1
        `RESULT_FLAG_CHECK(-1, 0, 1, 1, 0, "signed -5 % 2 carry");

        carryIn = 0;
        #1
        `RESULT_FLAG_CHECK(-1, 0, 1, 1, 0, "signed -5 % 2");

        b = 0;
        #1
        `DO_TEST(divByZero, 1, "signed 0 % 0; divide by zero is correct");

        carryIn = 1;
        #1
        `DO_TEST(divByZero, 1, "signed 0 % 0 carry; divide by zero is correct");

        op = INC;
        a = 2;
        #1
        `RESULT_FLAG_CHECK(3, 0, 0, 0, 0, "inc 2 carry");

        carryIn = 0;
        #1
        `RESULT_FLAG_CHECK(3, 0, 0, 0, 0, "inc 2");

        b = 5;
        #1
        `RESULT_FLAG_CHECK(3, 0, 0, 0, 0, "inc 2 b = 5");

        carryIn = 1;
        #1
        `RESULT_FLAG_CHECK(3, 0, 0, 0, 0, "inc 2 carry b = 5");

        op = DEC;
        a = 2;
        #1
        `RESULT_FLAG_CHECK(1, 0, 0, 0, 0, "dec 2 carry");

        carryIn = 0;
        #1
        `RESULT_FLAG_CHECK(1, 0, 0, 0, 0, "dec 2");

        b = 8;
        #1
        `RESULT_FLAG_CHECK(1, 0, 0, 0, 0, "dec 2 b = 8");

        carryIn = 1;
        #1
        `RESULT_FLAG_CHECK(1, 0, 0, 0, 0, "dec 2 carry b = 8");

        $finish();
    end

endmodule

tests/alu/arithmetic.vcd
$date
	Thu Apr 22 19:35:56 2021
$end
$version
	Icarus Verilog
$end
$timescale
	1s
$end
$scope module ArithmeticTest $end
$var wire 1 ! zero $end
$var wire 64 " result [63:0] $end
$var wire 1 # negitive $end
$var wire 1 $ divByZero $end
$var wire 1 % carry $end
$var reg 64 & a [63:0] $end
$var reg 64 ' b [63:0] $end
$var reg 1 ( carryIn $end
$var reg 16 ) op [15:0] $end
$scope module arith $end
$var wire 64 * a [63:0] $end
$var wire 64 + b [63:0] $end
$var wire 1 ( carryIn $end
$var wire 16 , op [15:0] $end
$var reg 1 % carry $end
$var reg 1 $ divByZero $end
$var reg 1 # negitive $end
$var reg 64 - result [63:0] $end
$var reg 64 . sa [63:0] $end
$var reg 64 / sb [63:0] $end
$var reg 1 ! zero $end
$upscope $end
$upscope $end
$scope module ICompare $end
$var wire 64 0 a [63:0] $end
$var wire 64 1 b [63:0] $end
$var reg 1 2 negitive $end
$var reg 64 3 result [63:0] $end
$var reg 1 4 zero $end
$upscope $end
$scope module IValue $end
$var wire 64 5 in [63:0] $end
$var wire 1 6 signExtend $end
$var wire 4 7 size [3:0] $end
$var reg 64 8 out [63:0] $end
$upscope $end
$enddefinitions $end
#0
$dumpvars
bx 8
bz 7
z6
bz 5
x4
bx 3
x2
bz 1
bz 0
b10 /
b1 .
b11 -
b1000 ,
b10 +
b1 *
b1000 )
0(
b10 '
b1 &
0%
0$
0#
b11 "
0!
$end
#1
b100 "
b100 -
1(
#2
1#
b1111111111111111111111111111111111111111111111111111111111111111 "
b1111111111111111111111111111111111111111111111111111111111111111 -
b1111111111111111111111111111111111111111111111111111111111111110 /
0(
b1111111111111111111111111111111111111111111111111111111111111110 '
b1111111111111111111111111111111111111111111111111111111111111110 +
#3
0#
1!
1%
b0 "
b0 -
1(
#4
1#
0!
0%
b1111111111111111111111111111111111111111111111111111111111111111 "
b1111111111111111111111111111111111111111111111111111111111111111 -
b0 /
b1111111111111111111111111111111111111111111111111111111111111111 .
0(
b0 '
b0 +
b1111111111111111111111111111111111111111111111111111111111111111 &
b1111111111111111111111111111111111111111111111111111111111111111 *
#5
0#
1!
1%
b0 "
b0 -
1(
#6
0!
b1 "
b1 -
b1 /
b1 '
b1 +
#7
0%
b10 "
b10 -
b11 .
0(
b11 &
b11 *
b1001 )
b1001 ,
#8
b1 "
b1 -
1(
#9
1#
1%
b1111111111111111111111111111111111111111111111111111111111111111 "
b1111111111111111111111111111111111111111111111111111111111111111 -
b11 /
b11 '
b11 +
#10
0#
1!
0%
b0 "
b0 -
0(
#11
1#
0!
b1111111111111111111111111111111111111111111111111111111111111101 "
b1111111111111111111111111111111111111111111111111111111111111101 -
b1 /
b1111111111111111111111111111111111111111111111111111111111111110 .
b1 '
b1 +
b1111111111111111111111111111111111111111111111111111111111111110 &
b1111111111111111111111111111111111111111111111111111111111111110 *
#12
b1111111111111111111111111111111111111111111111111111111111111100 "
b1111111111111111111111111111111111111111111111111111111111111100 -
1(
#13
1%
b1111111111111111111111111111111111111111111111111111111111111111 "
b1111111111111111111111111111111111111111111111111111111111111111 -
b1111111111111111111111111111111111111111111111111111111111111110 /
b1111111111111111111111111111111111111111111111111111111111111110 '
b1111111111111111111111111111111111111111111111111111111111111110 +
#14
0#
1!
0%
b0 "
b0 -
0(
#15
0!
b110 "
b110 -
b11 /
b10 .
b11 '
b11 +
b10 &
b10 *
b1010 )
b1010 ,
#16
1(
#17
1#
1%
b1111111111111111111111111111111111111111111111111111111111111110 "
b1111111111111111111111111111111111111111111111111111111111111110 -
b1111111111111111111111111111111111111111111111111111111111111111 /
0(
b1111111111111111111111111111111111111111111111111111111111111111 '
b1111111111111111111111111111111111111111111111111111111111111111 +
#18
1(
#19
0#
0%
b11 "
b11 -
b10 /
b110 .
b10 '
b10 +
b110 &
b110 *
b1011 )
b1011 ,
#20
0(
#21
b111111111111111111111111111111111111111111111111111111111111111 "
b111111111111111111111111111111111111111111111111111111111111111 -
b1111111111111111111111111111111111111111111111111111111111111110 .
b1111111111111111111111111111111111111111111111111111111111111110 &
b1111111111111111111111111111111111111111111111111111111111111110 *
#22
1(
#23
b1 "
b1 -
b1111111111111111111111111111111111111111111111111111111111111110 /
b1111111111111111111111111111111111111111111111111111111111111110 '
b1111111111111111111111111111111111111111111111111111111111111110 +
#24
0(
#25
x#
x!
x%
bx "
bx -
1$
b0 /
b0 '
b0 +
#26
1(
#27
0#
0!
0%
b11 "
b11 -
0$
b10 /
b110 .
b10 '
b10 +
b110 &
b110 *
b1101 )
b1101 ,
#28
0(
#29
1#
1%
b1111111111111111111111111111111111111111111111111111111111111101 "
b1111111111111111111111111111111111111111111111111111111111111101 -
b1111111111111111111111111111111111111111111111111111111111111110 /
b1111111111111111111111111111111111111111111111111111111111111110 '
b1111111111111111111111111111111111111111111111111111111111111110 +
#30
1(
#31
x#
x!
x%
bx "
bx -
1$
b0 /
b0 '
b0 +
#32
0(
#33
0#
0!
0%
b10 "
b10 -
0$
b11 /
b10 .
b11 '
b11 +
b10 &
b10 *
b1100 )
b1100 ,
#34
1(
#35
b1 "
b1 -
b100 .
b100 &
b100 *
#36
0(
#37
b100 "
b100 -
b1111111111111111111111111111111111111111111111111111111111111101 /
b1111111111111111111111111111111111111111111111111111111111111101 '
b1111111111111111111111111111111111111111111111111111111111111101 +
#38
1(
#39
b1 "
b1 -
b10 /
b1111111111111111111111111111111111111111111111111111111111111011 .
b10 '
b10 +
b1111111111111111111111111111111111111111111111111111111111111011 &
b1111111111111111111111111111111111111111111111111111111111111011 *
#40
0(
#41
x#
x!
x%
bx "
bx -
1$
b0 /
b0 '
b0 +
#42
1(
#43
0#
0!
0%
b10 "
b10 -
0$
b11 /
b10 .
b11 '
b11 +
b10 &
b10 *
b1110 )
b1110 ,
#45
b1 "
b1 -
b100 .
b100 &
b100 *
#46
0(
#47
b1111111111111111111111111111111111111111111111111111111111111101 /
b1111111111111111111111111111111111111111111111111111111111111101 '
b1111111111111111111111111111111111111111111111111111111111111101 +
#48
1(
#49
1#
1%
b1111111111111111111111111111111111111111111111111111111111111111 "
b1111111111111111111111111111111111111111111111111111111111111111 -
b10 /
b1111111111111111111111111111111111111111111111111111111111111011 .
b10 '
b10 +
b1111111111111111111111111111111111111111111111111111111111111011 &
b1111111111111111111111111111111111111111111111111111111111111011 *
#50
0(
#51
x#
x!
x%
bx "
bx -
1$
b0 /
b0 '
b0 +
#52
1(
#53
0#
0!
0%
b11 "
b11 -
0$
b10 .
b10 &
b10 *
b1111 )
b1111 ,
#54
0(
#55
b101 /
b101 '
b101 +
#56
1(
#57
b1 "
b1 -
b10000 )
b10000 ,
#58
0(
#59
b1000 /
b1000 '
b1000 +
#60
1(
