rtl/instructions.svh
`ifndef CPU_INSTRUCTIONS
`define CPU_INSTRUCTIONS

`include "rtl/types.svh"
import types::*;

package instructions;

typedef enum logic[15:0] {

    NOP,
    HALT,

    LOADMCR,
    STOREMCR,
    
    SYSCALL,
    SYSRET,
    INT,
    INTRET,

    ADD,
    SUB,
    MUL,

    UDIV,
    UMOD,

    SDIV,
    SMOD,

    INC,
    DEC,

    FADD,
    FSUB,
    FMUL,
    FDIV,
    FMOD,
    FFMA,

    FEPOW, // e ^ x
    F2POW, // 2 ^ x
    F10POW, // 10 ^ x
    FEPOW1, // e ^ x - 1
    F2POW1, // 2 ^ x - 1
    F10POW1, // 10 ^ x - 1

    FLN, // ln(x)
    F2LOG, // log2(x)
    F10LOG, // log10(x)
    FLN1, // ln(x + 1)
    F2LOG1, // log2(x + 1)
    F10LOG1, // log10(x + 1)

    FDISTANCE, // sqrt(x ^ 2 + y ^ 2)

    FSQRT,

    FPOW1, // (1 + x) ^ y
    FFPOW, // x ^ (1 / y)
    FPOW, // x ^ y
    
    FSIN,
    FCOS,
    FTAN,

    FASIN, // arcsin(x)
    FACOS, // arccos(x)
    FATAN, // arctan(x)
    FATAN2, // atan2(x, y)

    FSINPI, // sin(PI * x)
    FCOSPI, // cos(PI * x)
    FTANPI, // tan(PI * x)

    FASINPI, // arcsin(x) / PI
    FACOSPI, // arccos(x) / PI
    FATANPI, // arctan(x) / PI
    FATAN2PI, // atan2(x, y) / PI

    FSINH, // sinh(x)
    FCOSH, // cosh(x)
    FTANH, // tanh(x)

    FARSINH, // arsinh(x)
    FARCOSH, // arcosh(x)
    FARTANH, // artanh(x)

    FABS,
    FNEG,
    FCOPY,
    FTEST,

    TOINT,
    TOFLOAT,

    AND,
    OR,
    XOR,
    NOT,
    ROLR,
    ROLL,
    SHIFTR,
    SHIFTL,
    FLIP,

    SWAP,
    MOVE,

    CMP,

    JMP,
    BRA,
    RET,

    LOAD,
    STORE,
    STOREIF, // Only stores if value matches

    PUSH,
    POP,

    BIT,

    OUT,
    IN,

    SETF,
    CLEARF

} opcode_t;

typedef enum logic[3:0] {
    BITS_8 =   'h0,
    BITS_16 =  'h1,
    BITS_32 =  'h2,
    BITS_64 =  'h3
} sizeFlags_t;

typedef logic[7:0] flags_t;

`define NO_FLAGS 0

`define USE_ARG0_AS_IMMIDIATE (1<<0)
`define USE_ARG1_AS_IMMIDIATE (1<<1)
`define USE_ARG2_AS_IMMIDIATE (1<<2)
`define USE_ARG3_AS_IMMIDIATE (1<<3)

`define IS_FLOAT_NAN (1<<1)
`define IS_FLOAT_POS_NAN (1<<2)
`define IS_FLOAT_NEG_NAN (1<<3)
`define IS_FLOAT_INF (1<<4)
`define IS_FLOAT_POS_INF (1<<5)
`define IS_FLOAT_NEG_INF (1<<6)

`define ROUND_TO_NEAREST_EVEN (1<<2)
`define ROUND_TO_NEAREST_ZERO (1<<3)
`define ROUND_TO_ZERO (1<<4)
`define ROUND_TO_INF (1<<5)
`define ROUND_TO_NEG_INF (1<<6)

`define USE_CARRY_BIT (1<<2)

`define IS_RELATIVE (1<<4)

`define IS_ATOMIC (1<<4)

`define BIT_SET (1<<2)
`define BIT_CLEAR (1<<3)
`define BIT_TEST (1<<4)

`define SELECT_C_FLAG (1<<2)
`define SELECT_N_FLAG (1<<3)
`define SELECT_Z_FLAG (1<<4)

`define ARG0_SIGN_EXTEND (1<<4)
`define ARG1_SIGN_EXTEND (1<<5)
`define ARG2_SIGN_EXTEND (1<<6)
`define ARG3_SIGN_EXTEND (1<<7)

`define BRANCH_SIGNED (1<<0)
`define BRANCH_C (1<<1)
`define BRANCH_N (1<<2)
`define BRANCH_Z (1<<3)

`define BRANCH_NOT_C (1<<4)
`define BRANCH_NOT_N (1<<5)
`define BRANCH_NOT_z (1<<6)

typedef struct packed {
    opcode_t opcode;
    sizeFlags_t argSize0, argSize1, argSize2, argSize3;
    flags_t flags;
    ulong_t arg0, arg1, arg2, arg3;
} instruction_t;

endpackage

`endif

rtl/types.svh
`ifndef CPU_TYPES
`define CPU_TYPES

package types;

typedef logic signed[7:0] byte_t;
typedef logic signed[15:0] short_t;
typedef logic signed[31:0] int_t;
typedef logic signed[63:0] long_t;

typedef logic unsigned[7:0] ubyte_t;
typedef logic unsigned[15:0] ushort_t;
typedef logic unsigned[31:0] uint_t;
typedef logic unsigned[63:0] ulong_t;

typedef struct packed {
    logic sign;
    logic[4:0] exponent;
    logic[9:0] fraction;
} half_t;

typedef struct packed {
    logic sign;
    logic[7:0] exponent;
    logic[22:0] fraction;
} single_t;

typedef struct packed {
    logic sign;
    logic[10:0] exponent;
    logic[51:0] fraction;
} double_t;

typedef enum logic[1:0] {
    HALF,
    SINGLE,
    DOUBLE
} floatType_t;

typedef union packed {
    half_t half;
    single_t single;
    double_t double;
} floatValue_t;

typedef struct packed {
    floatType_t ftype;
    floatValue_t value;
} float_t;

endpackage

`endif

tests/testing.svh
`ifndef TESTING
`define TESTING

`define DO_TEST(value, expected, name) \
if (value == expected) \
    $display("Passed (%s, %0d [%0d]): %s", `__FILE__, `__LINE__, $realtime, name); \
else \
    $display("Failed (%s, %0d [%0d]): %s", `__FILE__, `__LINE__, $realtime, name);

`endif

rtl/alu/value.sv
`include "rtl/types.svh"
`include "rtl/instructions.svh"

import types::*;
import instructions::*;

module IValue(
    input ulong_t in,
    output ulong_t out,

    input sizeFlags_t size,
    input logic signExtend
);

    always @* begin
        case (size)
            BITS_8: begin
                if (signExtend)
                    out <= {{56{in[7]}}, in[7:0]};
                else
                    out <= {56'b0, in[7:0]};
            end
            BITS_16: begin
                if (signExtend)
                    out <= {{48{in[15]}}, in[15:0]};
                else
                    out <= {48'b0, in[15:0]};
            end
            BITS_32: begin
                if (signExtend)
                    out <= {{32{in[31]}}, in[31:0]};
                else
                    out <= {32'b0, in[31:0]};
            end
            BITS_64:
                out <= in;
        endcase
    end

endmodule

tests/alu/value.sv
`include "tests/testing.svh"

`include "rtl/types.svh"
`include "rtl/instructions.svh"

import types::*;
import instructions::*;

module IValueTest();
    ulong_t value;
    ulong_t result;
    sizeFlags_t size;
    logic signExtend;

    IValue ivalue(
        value,
        result,
        size,
        signExtend
    );

    initial begin
        value = 0;
        size = BITS_8;
        signExtend = 0;
    end

    initial begin
        $dumpfile(`DUMP_FILE);
        $dumpvars();

        value = -1;
        size = BITS_8;
        signExtend = 0;
        #1
        `DO_TEST(result, 8'hff, "8 bit zero extend");

        signExtend = 1;
        #1
        `DO_TEST(result, -1, "8 bit sign extend");

        value = 1;
        #1
        `DO_TEST(result, 1, "8 bit sign extend 2");

        value = -1;
        size = BITS_16;
        signExtend = 0;
        #1
        `DO_TEST(result, 16'hffff, "16 bit zero extend");

        signExtend = 1;
        #1
        `DO_TEST(result, -1, "16 bit sign extend");

        value = 1;
        #1
        `DO_TEST(result, 1, "16 bit sign extend 2");

        value = -1;
        size = BITS_32;
        signExtend = 0;
        #1
        `DO_TEST(result, 32'hffffffff, "32 bit zero extend");

        signExtend = 1;
        #1
        `DO_TEST(result, -1, "32 bit sign extend");

        value = 1;
        #1
        `DO_TEST(result, 1, "32 bit sign extend 2");

        value = -1;
        size = BITS_64;
        signExtend = 0;
        #1
        `DO_TEST(result, -1, "64 bit zero extend");

        signExtend = 1;
        #1
        `DO_TEST(result, -1, "64 bit sign extend");

        value = 1;
        #1
        `DO_TEST(result, 1, "64 bit sign extend 2");


        $finish();
    end
endmodule

rtl/alu/compare.sv
`include "rtl/types.svh"

import types::*;

module ICompare(
    input ulong_t a, b,

    output logic zero, negitive
);
    ulong_t result;

    // Sign extend / Zero extend
    always @* begin
        result <= a - b;

        zero <= result == 0;
        negitive <= result[63];
    end

endmodule

rtl/alu/arithmetic.sv
`include "rtl/types.svh"
`include "rtl/instructions.svh"

import types::*;
import instructions::*;

module Arithmetic(
    input opcode_t op,
    
    input logic carryIn,

    input ulong_t a, b,
    output ulong_t result,

    output logic divByZero,

    output logic zero, carry, negitive
);

    long_t sa, sb;

    always @* begin
        sa <= a;
        sb <= b;

        zero <= result == 0;
        negitive <= result[63];

        divByZero <=
            ((op == SDIV) || (op == UDIV) || (op == SMOD) || (op == UMOD)) &&
            b == 0;

        case (op)
            ADD: {carry, result} <= a + b + carryIn;
            SUB: {carry, result} <= a - b - carryIn;
            MUL: {carry, result} <= a * b;

            UDIV: {carry, result} <= a / b;
            UMOD: {carry, result} <= a % b;

            SDIV: {carry, result} <= sa / sb;
            SMOD: {carry, result} <= sa % sb;

            INC: {carry, result} <= a + 1;
            DEC: {carry, result} <= a - 1;
        endcase
    end

endmodule

tests/alu/value.vcd
$date
	Thu Apr 22 19:35:56 2021
$end
$version
	Icarus Verilog
$end
$timescale
	1s
$end
$scope module Arithmetic $end
$var wire 64 ! a [63:0] $end
$var wire 64 " b [63:0] $end
$var wire 1 # carryIn $end
$var wire 16 $ op [15:0] $end
$var reg 1 % carry $end
$var reg 1 & divByZero $end
$var reg 1 ' negitive $end
$var reg 64 ( result [63:0] $end
$var reg 64 ) sa [63:0] $end
$var reg 64 * sb [63:0] $end
$var reg 1 + zero $end
$upscope $end
$scope module ICompare $end
$var wire 64 , a [63:0] $end
$var wire 64 - b [63:0] $end
$var reg 1 . negitive $end
$var reg 64 / result [63:0] $end
$var reg 1 0 zero $end
$upscope $end
$scope module IValueTest $end
$var wire 64 1 result [63:0] $end
$var reg 1 2 signExtend $end
$var reg 4 3 size [3:0] $end
$var reg 64 4 value [63:0] $end
$scope module ivalue $end
$var wire 64 5 in [63:0] $end
$var wire 1 2 signExtend $end
$var wire 4 6 size [3:0] $end
$var reg 64 7 out [63:0] $end
$upscope $end
$upscope $end
$enddefinitions $end
#0
$dumpvars
b11111111 7
b0 6
b1111111111111111111111111111111111111111111111111111111111111111 5
b1111111111111111111111111111111111111111111111111111111111111111 4
b0 3
02
b11111111 1
x0
bx /
x.
bz -
bz ,
x+
bz *
bz )
bx (
x'
x&
x%
bz $
z#
bz "
bz !
$end
#1
b1111111111111111111111111111111111111111111111111111111111111111 1
b1111111111111111111111111111111111111111111111111111111111111111 7
12
#2
b1 1
b1 7
b1 4
b1 5
#3
b1111111111111111 1
b1111111111111111 7
02
b1 3
b1 6
b1111111111111111111111111111111111111111111111111111111111111111 4
b1111111111111111111111111111111111111111111111111111111111111111 5
#4
b1111111111111111111111111111111111111111111111111111111111111111 1
b1111111111111111111111111111111111111111111111111111111111111111 7
12
#5
b1 1
b1 7
b1 4
b1 5
#6
b11111111111111111111111111111111 1
b11111111111111111111111111111111 7
02
b10 3
b10 6
b1111111111111111111111111111111111111111111111111111111111111111 4
b1111111111111111111111111111111111111111111111111111111111111111 5
#7
b1111111111111111111111111111111111111111111111111111111111111111 1
b1111111111111111111111111111111111111111111111111111111111111111 7
12
#8
b1 1
b1 7
b1 4
b1 5
#9
b1111111111111111111111111111111111111111111111111111111111111111 1
b1111111111111111111111111111111111111111111111111111111111111111 7
02
b11 3
b11 6
b1111111111111111111111111111111111111111111111111111111111111111 4
b1111111111111111111111111111111111111111111111111111111111111111 5
#10
12
#11
b1 1
b1 7
b1 4
b1 5
